{
  "feature": "capability-calibration",
  "startedAt": "2026-06-15T07:46:13.907641Z",
  "currentStep": "done",
  "steps": {
    "code": {
      "status": "done",
      "completedAt": "2026-06-15T11:15:59Z"
    },
    "docs": {
      "status": "done",
      "completedAt": "2026-06-15T12:33:22Z"
    },
    "plan": {
      "status": "done",
      "completedAt": "2026-06-15T10:44:25Z"
    },
    "tests": {
      "status": "done",
      "completedAt": "2026-06-15T12:04:37Z"
    },
    "validate": {
      "status": "done",
      "completedAt": "2026-06-15T12:31:34Z"
    }
  },
  "stepOrder": [
    "plan",
    "code",
    "tests",
    "validate",
    "docs"
  ],
  "orchestrationMode": "strict-subagents-v1",
  "archetype": "canonical",
  "worktreePath": ".worktrees/capability-calibration"
}