{
  "feature": "simplify-output-prefix-emojis",
  "startedAt": "2026-04-06T21:16:18.645193Z",
  "currentStep": "code",
  "steps": {
    "code": {
      "status": "in-progress",
      "completedAt": null
    },
    "docs": {
      "status": "pending",
      "completedAt": null
    },
    "plan": {
      "status": "done",
      "completedAt": "2026-04-06T21:17:58Z"
    },
    "tests": {
      "status": "pending",
      "completedAt": null
    },
    "validate": {
      "status": "pending",
      "completedAt": null
    }
  },
  "stepOrder": [
    "plan",
    "code",
    "tests",
    "validate",
    "docs"
  ],
  "orchestrationMode": "strict-subagents-v1"
}